{
  "products": [
    {
      "image":
        "https://www.shoecarnival.com/dw/image/v2/BBSZ_PRD/on/demandware.static/-/Sites-scvl-master-catalog/default/dw99260205/13534_158565_1.jpg?sh=400",
      "brand": "Vans",
      "name": "SK8-HI",
      "price": "15"
    },
    {
      "image":
        "https://www.shoecarnival.com/dw/image/v2/BBSZ_PRD/on/demandware.static/-/Sites-scvl-master-catalog/default/dwf9ad2aaa/91632_175891_1.jpg?sh=400",
      "brand": "Nike",
      "name": "Flywire",
      "price": "20"
    },
    {
      "image":
        "https://www.shoecarnival.com/dw/image/v2/BBSZ_PRD/on/demandware.static/-/Sites-scvl-master-catalog/default/dw5510c6a2/93931_180789_1.jpg?sw=1694&sh=1999&sm=fit",
      "brand": "Puma",
      "name": "Smash Pro",
      "price": "22"
    },
    {
      "image":
        "https://i.pinimg.com/originals/ea/df/f6/eadff6bc12137a578d29beaa181f1036.jpg",
      "brand": "Vans",
      "name": "Old Skool",
      "price": "18"
    },
    {
      "image":
        "http://www.mypmsite.com/images/large/vans%20shoes/Vans%20Low%20top%20trainers%20LPE%20DRESS%20%20BLUES%20%20Polk...0OO_LRG.jpg",
      "brand": "Vans",
      "name": "Authentic Sneakers",
      "price": "20"
    },
    {
      "image":
        "http://www.colinandsuespence.com/images/examcentral/LDY7220000880.jpg",
      "brand": "Adidas",
      "name": "Adi-Rise Mid",
      "price": "25"
    },
    {
      "image":
        "http://www.kmart.com.au/wcsstore/Kmart/images/ncatalog/sz/0/67733750-1-sz.jpg",
      "brand": "Nike",
      "name": "Air Melo Line",
      "price": "25"
    },
    {
      "image":
        "http://www.colinandsuespence.com/images/examcentral/RMD22300001979.jpg",
      "brand": "Vans",
      "name": "Slip-On Runners",
      "price": "16"
    }
  ]
}
